calcpad/__init__.py
calcpad-0.0.0.dist-info/METADATA
calcpad-0.0.0.dist-info/WHEEL
calcpad-0.0.0.dist-info/top_level.txt
calcpad-0.0.0.dist-info/RECORD
