Metadata-Version: 2.4
Name: calcpad
Version: 0.0.0
Summary: Coming soon
Author-email: Chris Taylor <c.taylor@ci-eng.co.uk>
